{"assets/ExamRegn_EFATBCM031_13-04-2022.pdf":["assets/ExamRegn_EFATBCM031_13-04-2022.pdf"],"assets/bg.png":["assets/bg.png"],"assets/cat1.png":["assets/cat1.png"],"assets/cat2.png":["assets/cat2.png"],"assets/cat3.png":["assets/cat3.png"],"assets/cat4.png":["assets/cat4.png"],"assets/cat5.png":["assets/cat5.png"],"assets/dedicateddesk.png":["assets/dedicateddesk.png"],"assets/map.jpg":["assets/map.jpg"],"assets/officesuite.png":["assets/officesuite.png"],"assets/projector.png":["assets/projector.png"],"assets/projectorscreen.png":["assets/projectorscreen.png"],"assets/spaceprivate.png":["assets/spaceprivate.png"],"assets/wifi.png":["assets/wifi.png"],"packages/cupertino_icons/assets/CupertinoIcons.ttf":["packages/cupertino_icons/assets/CupertinoIcons.ttf"]}